lstpy/__init__.py
lstpy/_version.py
lstpy/load.py
lstpy/utils.py
lstpy-0.0.5.dist-info/METADATA
lstpy-0.0.5.dist-info/WHEEL
lstpy-0.0.5.dist-info/top_level.txt
lstpy-0.0.5.dist-info/RECORD
